README.md
setup.py
ediri_scaleway/__init__.py
ediri_scaleway/_inputs.py
ediri_scaleway/_utilities.py
ediri_scaleway/account_project.py
ediri_scaleway/account_ssh_key.py
ediri_scaleway/apple_silicon_server.py
ediri_scaleway/baremetal_server.py
ediri_scaleway/block_snapshot.py
ediri_scaleway/block_volume.py
ediri_scaleway/cockpit.py
ediri_scaleway/cockpit_alert_manager.py
ediri_scaleway/cockpit_grafana_user.py
ediri_scaleway/cockpit_source.py
ediri_scaleway/cockpit_token.py
ediri_scaleway/container.py
ediri_scaleway/container_cron.py
ediri_scaleway/container_domain.py
ediri_scaleway/container_namespace.py
ediri_scaleway/container_token.py
ediri_scaleway/container_trigger.py
ediri_scaleway/documentdb_database.py
ediri_scaleway/documentdb_instance.py
ediri_scaleway/documentdb_private_network_endpoint.py
ediri_scaleway/documentdb_privilege.py
ediri_scaleway/documentdb_read_replica.py
ediri_scaleway/documentdb_user.py
ediri_scaleway/domain_record.py
ediri_scaleway/domain_zone.py
ediri_scaleway/flexible_ip.py
ediri_scaleway/flexible_ip_mac_address.py
ediri_scaleway/function.py
ediri_scaleway/function_cron.py
ediri_scaleway/function_domain.py
ediri_scaleway/function_namespace.py
ediri_scaleway/function_token.py
ediri_scaleway/function_trigger.py
ediri_scaleway/get_account_project.py
ediri_scaleway/get_account_ssh_key.py
ediri_scaleway/get_availability_zones.py
ediri_scaleway/get_baremetal_offer.py
ediri_scaleway/get_baremetal_option.py
ediri_scaleway/get_baremetal_os.py
ediri_scaleway/get_baremetal_server.py
ediri_scaleway/get_billing_consumptions.py
ediri_scaleway/get_billing_invoices.py
ediri_scaleway/get_block_snapshot.py
ediri_scaleway/get_block_volume.py
ediri_scaleway/get_cockpit.py
ediri_scaleway/get_cockpit_plan.py
ediri_scaleway/get_config.py
ediri_scaleway/get_container.py
ediri_scaleway/get_container_namespace.py
ediri_scaleway/get_documentdb_database.py
ediri_scaleway/get_documentdb_instance.py
ediri_scaleway/get_documentdb_load_balancer_endpoint.py
ediri_scaleway.egg-info/PKG-INFO
ediri_scaleway.egg-info/SOURCES.txt
ediri_scaleway.egg-info/dependency_links.txt
ediri_scaleway.egg-info/not-zip-safe
ediri_scaleway.egg-info/requires.txt
ediri_scaleway.egg-info/top_level.txt
