Metadata-Version: 2.1
Name: ediri-scaleway
Version: 2.47.0
Summary: A Pulumi package for creating and managing Scaleway resources.
Home-page: https://www.pulumi.com
License: Apache-2.0
Project-URL: Repository, https://github.com/dirien/pulumi-scaleway
Keywords: pulumi scaleway category/utility
Platform: UNKNOWN
Requires-Python: >=3.8
